regexexercises/__init__.py
regexexercises/app_guide.md
regexexercises/pyregex_exercises.css
regexexercises/pyregex_exercises.py
regexexercises/questions.json
regexexercises/user_progress.json
regexexercises-2.1.0.dist-info/METADATA
regexexercises-2.1.0.dist-info/WHEEL
regexexercises-2.1.0.dist-info/entry_points.txt
regexexercises-2.1.0.dist-info/licenses/LICENSE
regexexercises-2.1.0.dist-info/RECORD
