Metadata-Version: 2.4
Name: regexexercises
Version: 2.1.0
Summary: 100+ exercises for Python Regular Expressions
Project-URL: Source, https://github.com/learnbyexample/TUI-apps/tree/main/PyRegexExercises
Project-URL: Issues, https://github.com/learnbyexample/TUI-apps/issues
Author-email: Sundeep Agarwal <learnbyexample.net@gmail.com>
License-File: LICENSE
Classifier: License :: OSI Approved :: MIT License
Classifier: Operating System :: OS Independent
Classifier: Programming Language :: Python :: 3
Requires-Python: >=3.9
Requires-Dist: regex
Requires-Dist: textual==0.85.2
